vizhelper/__init__.py
vizhelper/enhance.py
vizhelper-0.2.1.dist-info/METADATA
vizhelper-0.2.1.dist-info/WHEEL
vizhelper-0.2.1.dist-info/top_level.txt
vizhelper-0.2.1.dist-info/RECORD
