Metadata-Version: 2.4
Name: vizhelper
Version: 0.2.1
Summary: A user-centered visualization helper for Matplotlib
Author: Ahmad Ughurluzada
Requires-Dist: matplotlib
Requires-Dist: pandas
Requires-Dist: mplcursors
Requires-Dist: openai
Dynamic: author
Dynamic: description
Dynamic: description-content-type
Dynamic: requires-dist
Dynamic: summary
